Workbook

Sheet Инциденты
A1: № | B1: Дата | C1: № сотрудника | D1: Должность / Подразделение | E1: Канал передачи / Источник | F1: Описание инцидента и передаваемые данные | G1: Объем / Специфика | H1: Тип инцидента | I1: Категория данных | J1: Бота нет | K1: Рецидив | L1: Неверефицированный получатель / Необратимость | M1: Умысел (инсайдер) | N1: Масштаб | O1: Балл риска события
A2: 8 | B2: 03.06 | C2: 8 | D2: Главный специалист по учету расходных материалов | E2: Telegram | F2: Отправила в Telegram-чат таблицу с актуальными логином и паролем от УЗ User_8 в Active Directory и корпоративном сервисе Google Workspace | G2: Логин/пароль доменной УЗ + Google Workspace | H2: A1 | I2: D1 | J2: 1 | K2: 0 | L2: 0 | M2: 0 | N2: 0 | O2: =VLOOKUP($H2, Справочник!$A$2:$B$5, 2)*VLOOKUP($I2, Справочник!$D$2:$E$5, 2)+SUM($J2:$N2) -> 9 | Q2: Пояснения | S2: Формула
A3: 20 | B3: 09.06 | C3: 20 | D3: Специалист технической поддержки / Группа ТП | E3: USB-накопитель | F3: Скопировал на внешний накопитель папки с конфиденциальной информацией из сетевого ресурса, включая ПДн пациентов, сканы паспортов, счета на оплату и медицинскую документацию | G3: 30 строк ПДн пациентов, сканы паспортов, счета; USB\General_UDisk_Device | H3: A2 | I3: D2 | J3: 0 | K3: 0 | L3: 1 | M3: 2 | N3: 0 | O3: =VLOOKUP($H3, Справочник!$A$2:$B$5, 2)*VLOOKUP($I3, Справочник!$D$2:$E$5, 2)+SUM($J3:$N3) -> 8.1 | Q3: Типы инцидента: A1 - Передача данных внешнему получателю A2 - Передача данных в некотролируемую среду (хранилище/канал связи) A3 - Нарушение мер технического контроля A4 - Риск индикатор (есть мотив, но факта утечки нет) | R3: Категории данных: D1 - Учетные данные от инфраструктуры D2 - Спец ПДн например, врачебная тайна D3 - Коммерческая тайна (финансово коммерческие данные) D4 - ПДн сотрудников или пациентов (ФИО, паспортные данные без медицинских полей) D5 - Внутренние регламенты/документы/процессы в сети D6 - Нет утечки данных | S3: Балл Риска = AX*DX+доп.веса
A4: 9 | B4: 03.06 | C4: 9 | D4: Младший менеджер по ценообразованию услуг | E4: Telegram | F4: Отправила таблицу с план/факт выручкой за май (тек./прошл. год), приростом и маржой по категориям медуслуг. Получатель не подтвержден (в AD есть с идентичным ФИО) | G4: XLSX, 3 листа (3 региона) | H4: A1 | I4: D3 | J4: 1 | K4: 0 | L4: 1 | M4: 0 | N4: 0 | O4: =VLOOKUP($H4, Справочник!$A$2:$B$5, 2)*VLOOKUP($I4, Справочник!$D$2:$E$5, 2)+SUM($J4:$N4) -> 8
A5: 19 | B5: 09.06 | C5: 19 | D5: Менеджер по медицинскому маркетингу / Отдел маркетинга | E5: Telegram | F5: Отправила в Telegram-чат таблицу с себестоимостью медицинских исследований | G5: XLSX, 6409 строк (массовый объем) | H5: A1 | I5: D3 | J5: 1 | K5: 0 | L5: 0 | M5: 0 | N5: 1 | O5: =VLOOKUP($H5, Справочник!$A$2:$B$5, 2)*VLOOKUP($I5, Справочник!$D$2:$E$5, 2)+SUM($J5:$N5) -> 8
A6: 27 | B6: 17.06 | C6: 12 | D6: Заместитель директора по безопасности / Руководитель ОВК клиники | E6: Соцсеть (VK) | F6: Через VK отправил таблицу с данными по товарному запасу (услуга/препарат, склад, физические остатки, категория, фин. сумма). Получателя с такой фамилией в компании нет | G6: XLSX, 1831 строка; получатель вне организации; ПОВТОРНО (12: инц. 12 + 27) | H6: A1 | I6: D3 | J6: 0 | K6: 0 | L6: 1 | M6: 0 | N6: 1 | O6: =VLOOKUP($H6, Справочник!$A$2:$B$5, 2)*VLOOKUP($I6, Справочник!$D$2:$E$5, 2)+SUM($J6:$N6) -> 8
A7: 42 | B7: 28.06 | C7: 42 | D7: Аккаунт-менеджер по работе с партнерскими лабораториями | E7: Соцсеть (VK) | F7: Отправила в «Избранное» соцсети таблицу с учетными данными авторизации (почта/пароль) к личному кабинету МИС | G7: XLSX, 254 строки учетных данных | H7: A2 | I7: D1 | J7: 1 | K7: 0 | L7: 0 | M7: 0 | N7: 1 | O7: =VLOOKUP($H7, Справочник!$A$2:$B$5, 2)*VLOOKUP($I7, Справочник!$D$2:$E$5, 2)+SUM($J7:$N7) -> 8
A8: 25 | B8: 16.06 | C8: 25 | D8: Директор филиала / Руководители | E8: Публичный ИИ-сервис | F8: Выгрузила в публичный ИИ-сервис таблицу с показателями: направление услуг, маржа %, выручка руб., количество приемов | G8: XLSX, 691 строка | H8: A1 | I8: D3 | J8: 0 | K8: 0 | L8: 1 | M8: 0 | N8: 1 | O8: =VLOOKUP($H8, Справочник!$A$2:$B$5, 2)*VLOOKUP($I8, Справочник!$D$2:$E$5, 2)+SUM($J8:$N8) -> 8
A9: 30 | B9: 21.06 | C9: 30 | D9: Data-аналитик по ценообразованию | E9: Публичный ИИ-сервис | F9: ы | G9: XLSX; данные по всей сети | H9: A1 | I9: D3 | J9: 0 | K9: 0 | L9: 1 | M9: 0 | N9: 1 | O9: =VLOOKUP($H9, Справочник!$A$2:$B$5, 2)*VLOOKUP($I9, Справочник!$D$2:$E$5, 2)+SUM($J9:$N9) -> 8
A10: 34 | B10: 22.06 | C10: 34 | D10: Управляющий филиалом / Клиника | E10: Публичный ИИ-сервис | F10: Отправила в публичный ИИ-сервис таблицу с промптом на анализ: полные финансовые и операционные показатели медцентра за 2 года (выручка, план, трафик, средний чек, маржа, ФОТ врачей) | G10: XLSX; полные показатели филиала за 2 года | H10: A1 | I10: D3 | J10: 0 | K10: 0 | L10: 1 | M10: 0 | N10: 1 | O10: =VLOOKUP($H10, Справочник!$A$2:$B$5, 2)*VLOOKUP($I10, Справочник!$D$2:$E$5, 2)+SUM($J10:$N10) -> 8
A11: 43 | B11: 30.06 | C11: 43 | D11: Специалист по отменам и возвратам онлайн-записей | E11: Соцсеть (VK) | F11: Отправила в чат соцсети таблицу с ПДн и врачебной тайной пациентов (ФИО, телефон, e-mail, адрес, назначенные процедуры) | G11: XLSX, 26 строк; спец. категории ПДн | H11: A1 | I11: D2 | J11: 1 | K11: 0 | L11: 0 | M11: 0 | N11: 0 | O11: =VLOOKUP($H11, Справочник!$A$2:$B$5, 2)*VLOOKUP($I11, Справочник!$D$2:$E$5, 2)+SUM($J11:$N11) -> 7.8
A12: 1 | B12: 01.06 | C12: 1 | D12: Директор подразделения | E12: Telegram | F12: Отправил в Telegram-чат таблицу с информацией по выручке по месяцам на филиале | G12: XLSX-файл; выручка филиала | H12: A1 | I12: D3 | J12: 1 | K12: 0 | L12: 0 | M12: 0 | N12: 0 | O12: =VLOOKUP($H12, Справочник!$A$2:$B$5, 2)*VLOOKUP($I12, Справочник!$D$2:$E$5, 2)+SUM($J12:$N12) -> 7
A13: 16 | B13: 08.06 | C13: 16 | D13: Менеджер по обеспечению препаратами | E13: Telegram | F13: Отправила в Telegram-чат таблицу с себестоимостью медицинских препаратов и расходников | G13: XLSX, 129 строк | H13: A1 | I13: D3 | J13: 1 | K13: 0 | L13: 0 | M13: 0 | N13: 0 | O13: =VLOOKUP($H13, Справочник!$A$2:$B$5, 2)*VLOOKUP($I13, Справочник!$D$2:$E$5, 2)+SUM($J13:$N13) -> 7
A14: 17 | B14: 08.06 | C14: 17 | D14: Главный врач филиала / Руководители | E14: Telegram | F14: Отправила в Telegram-чат таблицу с данными по маржинальности высокотехнологичных медицинских услуг | G14: XLSX, 445 строк на 3 листах | H14: A1 | I14: D3 | J14: 1 | K14: 0 | L14: 0 | M14: 0 | N14: 0 | O14: =VLOOKUP($H14, Справочник!$A$2:$B$5, 2)*VLOOKUP($I14, Справочник!$D$2:$E$5, 2)+SUM($J14:$N14) -> 7
A15: 35 | B15: 23.06 | C15: 35 | D15: Старший менеджер по работе с контрагентами | E15: Telegram | F15: Хранит логины и пароли партнеров от корпоративных ресурсов в Telegram | G15: УЗ партнеров в мессенджере | H15: A2 | I15: D1 | J15: 1 | K15: 0 | L15: 0 | M15: 0 | N15: 0 | O15: =VLOOKUP($H15, Справочник!$A$2:$B$5, 2)*VLOOKUP($I15, Справочник!$D$2:$E$5, 2)+SUM($J15:$N15) -> 7
... A44: 36 | B44: 23.06 | C44: 36 | D44: Руководитель отдела по найму | E44: Карьерный сервис (HH.ru) | F44: Проходила собеседование на позицию «Директор по подбору» в сторонний крупный холдинг через кадровое агентство | G44: Собеседование через агентство | H44: A4 | I44: D6 | J44: 0 | K44: 0 | L44: 0 | M44: 1 | N44: 0 | O44: =VLOOKUP($H44, Справочник!$A$2:$B$5, 2)*VLOOKUP($I44, Справочник!$D$2:$E$5, 2)+SUM($J44:$N44) -> 2.3

Sheet Справочник
A1: Тип | B1: Вес | D1: Категория | E1: Вес | H1: Подробнее про типы инцидентов
A2: A1 | B2: 4 | D2: D1 | E2: 2 | H2: Типы инцидента: A1 - Передача данных внешнему получателю A2 - Передача данных в некотролируемую среду (хранилище/канал связи) A3 - Нарушение мер технического контроля A4 - Риск индикатор (есть мотив, но факта утечки нет) | I2: Категории данных: Д1 - Учетные данные от инфраструктуры Д2 - Спец ПДн например, врачебная тайна Д3 - Коммерческая тайна (финансово коммерческие данные) Д4 - ПДн сотрудников или пациентов (ФИО, паспортные данные без медицинских полей) Д5 - Внутренние регламенты/документы Д6 - Нет утечки данных
A3: A2 | B3: 3 | D3: D2 | E3: 1.7
A4: A3 | B4: 2 | D4: D3 | E4: 1.5
A5: A4 | B5: 1 | D5: D4 | E5: 1.3
D6: D5 | E6: 1.1
D7: D6 | E7: 1

Sheet Баллы риска пользователей
A1: № сотрудника | B1: Балл риска события | D1: Балл риска пользователя = Сумма баллов риска инцидента, где пользователь был вовлечен Как идея - можно также в балл риска пользователя внести доп вес в виде его доступов, для указания на критичность самого пользователя.
A2: 12 | B2: 10.6
A3: 8 | B3: 9
A4: 20 | B4: 8.1
A5: 9 | B5: 8
A6: 19 | B6: 8
A7: 25 | B7: 8
A8: 30 | B8: 8
A9: 34 | B9: 8
A10: 42 | B10: 8
A11: 43 | B11: 7.8
A12: 1 | B12: 7
A13: 16 | B13: 7
... A42: 36 | B42: 2.3

Sheet Виджет по источникам
A3: Названия строк | B3: Количество по полю Канал передачи / Источник
A4: Telegram | B4: 9
A5: Соцсеть (VK) | B5: 7
A6: Нарушение политики ИБ | B6: 6
A7: Публичный ИИ-сервис | B7: 5
A8: Карьерный сервис (HH.ru) | B8: 4
A9: МФО (фин. сервисы) | B9: 3
A10: Личное облако | B10: 3
A11: USB-накопитель | B11: 2
A12: Личная почта | B12: 2
A13: Нерегламентированное ПО (рабочий ПК) | B13: 1
A14: Букмекерский сайт | B14: 1
A15: Общий итог | B15: 43
